enhanced_quantum_backend_selector/__init__.py
enhanced_quantum_backend_selector/backend_analyzer.py
enhanced_quantum_backend_selector/backend_selector.py
enhanced_quantum_backend_selector/circuit_scorer.py
enhanced_quantum_backend_selector/models.py
enhanced_quantum_backend_selector-0.1.0.dist-info/METADATA
enhanced_quantum_backend_selector-0.1.0.dist-info/WHEEL
enhanced_quantum_backend_selector-0.1.0.dist-info/licenses/LICENSE
enhanced_quantum_backend_selector-0.1.0.dist-info/RECORD
