Metadata-Version: 2.4
Name: enhanced-quantum-backend-selector
Version: 0.1.0
Summary: Intelligent quantum backend selection for Qiskit circuits
License: Apache-2.0
License-File: LICENSE
Keywords: quantum,qiskit,backend,optimization,quantum-computing
Author: sevetseh28
Author-email: hernaner28@gmail.com
Requires-Python: >=3.10
Classifier: Development Status :: 3 - Alpha
Classifier: Intended Audience :: Science/Research
Classifier: Intended Audience :: Developers
Classifier: License :: OSI Approved :: Apache Software License
Classifier: Programming Language :: Python :: 3
Classifier: Programming Language :: Python :: 3.10
Classifier: Programming Language :: Python :: 3.11
Classifier: Programming Language :: Python :: 3.12
Classifier: Programming Language :: Python :: 3.13
Classifier: Topic :: Scientific/Engineering :: Physics
Classifier: Topic :: Software Development :: Libraries :: Python Modules
Classifier: Typing :: Typed
Provides-Extra: dev
Provides-Extra: docs
Requires-Dist: mkdocs (>=1.5.0) ; extra == "docs"
Requires-Dist: mkdocs-material (>=9.5.0) ; extra == "docs"
Requires-Dist: mkdocstrings[python] (>=0.24.0) ; extra == "docs"
Requires-Dist: mypy (>=1.18.2) ; extra == "dev"
Requires-Dist: pre-commit (>=3.5.0) ; extra == "dev"
Requires-Dist: pytest (>=8.0.0) ; extra == "dev"
Requires-Dist: pytest-cov (>=4.1.0) ; extra == "dev"
Requires-Dist: python-semantic-release (>=9.17.0) ; extra == "dev"
Requires-Dist: qiskit (>=2.2.3,<3.0.0)
Requires-Dist: qiskit-aer (>=0.17.2,<0.18.0) ; extra == "dev"
Requires-Dist: qiskit-ibm-runtime (>=0.45.0) ; extra == "dev"
Requires-Dist: ruff (>=0.6.0) ; extra == "dev"
Project-URL: Bug Tracker, https://github.com/sevetseh28/enhanced_quantum_backend_selector/issues
Project-URL: Changelog, https://github.com/sevetseh28/enhanced_quantum_backend_selector/blob/main/CHANGELOG.md
Project-URL: Documentation, https://sevetseh28.github.io/enhanced_quantum_backend_selector
Project-URL: Homepage, https://github.com/sevetseh28/enhanced_quantum_backend_selector
Project-URL: Repository, https://github.com/sevetseh28/enhanced_quantum_backend_selector
